pdffit/__init__.py
pdffit/distfit.py
pdffit/version.py
pyprobabilitydistributionfit-0.0.6.dist-info/METADATA
pyprobabilitydistributionfit-0.0.6.dist-info/WHEEL
pyprobabilitydistributionfit-0.0.6.dist-info/licenses/LICENSE
pyprobabilitydistributionfit-0.0.6.dist-info/RECORD
