Metadata-Version: 2.3
Name: pyProbabilityDistributionFit
Version: 0.0.6
Dynamic: Summary
Project-URL: Home, https://github.com/WolfgangFahl/pyProbabilityDistributionFit
Project-URL: Documentation, https://wiki.bitplan.com/index.php/PyProbabilityDistributionFit
Project-URL: Source, https://github.com/WolfgangFahl/pyProbabilityDistributionFit
Author-email: Wolfgang Fahl <wf@bitplan.com>
Maintainer-email: Wolfgang Fahl <wf@bitplan.com>
License-Expression: Apache-2.0
License-File: LICENSE
Classifier: Programming Language :: Python
Classifier: Programming Language :: Python :: 3.9
Classifier: Programming Language :: Python :: 3.10
Classifier: Programming Language :: Python :: 3.11
Classifier: Programming Language :: Python :: 3.12
Requires-Python: >=3.9
Requires-Dist: matplotlib>=3.5.2
Requires-Dist: pandas>=1.4.2
Requires-Dist: pdffit
Requires-Dist: statsmodels>=0.13.2
Requires-Dist: tornado>=6.1
Provides-Extra: test
